{
  "document_id": "ChinaRealEstateInformationCorp_20090929_F-1_EX-10.32_4771615_EX-10.32_Content License Agreement",
  "file_path": "data/CUAD_v1/full_contract_pdf/Part_I/License_Agreements/ChinaRealEstateInformationCorp_20090929_F-1_EX-10.32_4771615_EX-10.32_Content License Agreement.pdf",
  "text_length": 50071,
  "chunk_count": 69,
  "vector_store_path": "output/vector_stores/ChinaRealEstateInformationCorp_20090929_F-1_EX-10.32_4771615_EX-10.32_Content License Agreement",
  "summary": "proceeding have been paid.   \nARTICLE VI  \nTERM AND TERMINATION   \n6.1. Term . The initial term of this Agreement (the \u201cInitial Term \u201d) shall  commence on the Effective Date and shall continue for a period of ten (10) \nyears thereafter.  Beginning twelve (12) months prior to the expiration of the Initial Term, the Parties shall use   \n7  \nSource: CHINA REAL ESTATE INFORMATION CORP, F-1, 9/29/2009\n\n7.1. Representations and Warranties .  \n(a) By Each Party . Each of Licensee and Licensor represents and warrants to each  other Party that: (a) it is a corporation duly incorporated, validly \nexisting and in good standing  under applicable Law; (b) the execution, delivery and performance of this Agreement and the  consummation of the \ntransactions contemplated hereby are within its corporate powers; (c) it has  taken necessary steps to obtain authority and all necessary consents \nand approvals of any other  third party or Governmental Authority to execute and perform this Agreement; (d) this Agreement has  been duly \nexecuted and delivered by it and constitutes its valid and binding obligation,  enforceable against it in accordance with its terms, except as such \nenforceability may be limited  by bankruptcy, insolvency, reorganization, or other laws affecting the rights of creditors \u2019 generally or by general\n\nAgreement dated May 8, 2008 (the \u201cOriginal  Agreement \u201d) and (i) Licensor and SINA Leju desire to terminate the Original Agreement pursuant  to \nthe Mutual Termination Agreement attached hereto as Exhibit B  and (ii) Licensee and  Licensor desire to enter into this Agreement, on or prior to \nthe consummation of the transactions  contemplated by the Share Purchase Agreement.   \nNOW, THEREFORE, for and in consideration of the mutual covenants and agreement of the Parties  and the faithful performance thereof, and \nother good and valuable consideration, the receipt and  sufficiency of which are hereby acknowledged, the Parties hereto agree as follows:   \nARTICLE I  \nDEFINITIONS   \nAs used herein, the following terms shall have the meanings ascribed to them below.   \n\u201cAction\u201d\u00a0has the meaning set forth in Section 8.1.   \n\u201cAffiliate\u201d\u00a0means, when used with respect to any specified Person, a Person that  directly or indirectly through one or more intermediaries, controls,\n\nambiguities in this Agreement against the Party that drafted it has no application and is  expressly waived. If any claim is made by a Party relating \nto any conflict, omission or ambiguity  in the provisions of this Agreement, no presumption or burden of proof or persuasion will be  implied \nbecause this Agreement was prepared by or at the request of any Party or its counsel.   \n10.14. Specific Performance . The parties hereto acknowledge and agree that  irreparable damage would occur if any of the provisions of this \nAgreement are not performed in  accordance with their specific terms and that any breach of this Agreement could not be adequately  compensated \nin all cases by monetary damages alone. Accordingly, in addition to any other right or  remedy to which a party hereto may be entitled, at law or in \nequity, it shall be entitled to  enforce any provision of this Agreement by a decree of specific performance and to temporary,  preliminary and",
  "parties": "source unrelated to any Party and not under a duty of  confidentiality to the other Party.   \nARTICLE X  \nGENERAL PROVISIONS   \n10.1. Taxes . Each Party shall be responsible for taxes that should be borne by it in  accordance with applicable Law. If any Party pays any taxes that \nshould have been borne by the  other Party in accordance with Law, such other Party shall reimburse such Party within seven (7)  days after its \nreceipt of documentation evidencing such tax payment so incurred by such Party.   \n10.2. Expenses . Except as otherwise specified in this Agreement, all costs and  expenses, including, fees and disbursements of counsel, financial \nadvisors and accountants,  incurred in connection with this Agreement and the transactions contemplated by this Agreement  shall be borne by the \nparty incurring such costs and expenses, whether or not the Closing shall  have occurred.\n\n10.10. No Third Party Beneficiaries . Except for the provisions of Article VII  relating to indemnified parties, this Agreement shall be binding upon \nand inure solely to the  benefit of the Parties and their respective successors and permitted assigns and nothing herein,  express or implied \n(including the provisions of Article VII relating to indemnified parties), is  intended to or shall confer upon any other Person any legal or equitable \nright, benefit or remedy  of any nature whatsoever, including any rights of employment for any specified period, under or by  reason of this \nAgreement.   \n10.11. Governing Law . This Agreement and any dispute or claim arising out of or in  connection with it or its subject matter shall be governed by, \nand construed in accordance with,  the laws of the People \u2019s Republic of China (without regard to its conflicts of laws rules that  would mandate the \napplication of the laws of another jurisdiction).\n\nany court of competent jurisdiction. The  Parties shall use their best efforts to effect the prompt execution of any such award and shall  render \nwhatever assistance as may be necessary to this end. The prevailing Party (as determined by  the arbitrators) shall be entitled to reimbursement of \nits costs and expenses, including reasonable  attorney\u2019s fees, incurred in connection with the arbitration and any judicial enforcement, unless  the \narbitrators determine that it would be manifestly unfair to honor this agreement of the Parties  and determine a different allocation of costs.   \n(d) The foregoing provisions in this Section 10.12 shall not preclude any Party from seeking  interim or conservatory remedies, including injunctive \nrelief, from any court having jurisdiction  to grant such relief.   \n10.13. No Presumption . The Parties acknowledge that each has been represented by  counsel in connection with this Agreement and the\n\nambiguities in this Agreement against the Party that drafted it has no application and is  expressly waived. If any claim is made by a Party relating \nto any conflict, omission or ambiguity  in the provisions of this Agreement, no presumption or burden of proof or persuasion will be  implied \nbecause this Agreement was prepared by or at the request of any Party or its counsel.   \n10.14. Specific Performance . The parties hereto acknowledge and agree that  irreparable damage would occur if any of the provisions of this \nAgreement are not performed in  accordance with their specific terms and that any breach of this Agreement could not be adequately  compensated \nin all cases by monetary damages alone. Accordingly, in addition to any other right or  remedy to which a party hereto may be entitled, at law or in \nequity, it shall be entitled to  enforce any provision of this Agreement by a decree of specific performance and to temporary,  preliminary and",
  "key_terms": "7.1. Representations and Warranties .  \n(a) By Each Party . Each of Licensee and Licensor represents and warrants to each  other Party that: (a) it is a corporation duly incorporated, validly \nexisting and in good standing  under applicable Law; (b) the execution, delivery and performance of this Agreement and the  consummation of the \ntransactions contemplated hereby are within its corporate powers; (c) it has  taken necessary steps to obtain authority and all necessary consents \nand approvals of any other  third party or Governmental Authority to execute and perform this Agreement; (d) this Agreement has  been duly \nexecuted and delivered by it and constitutes its valid and binding obligation,  enforceable against it in accordance with its terms, except as such \nenforceability may be limited  by bankruptcy, insolvency, reorganization, or other laws affecting the rights of creditors \u2019 generally or by general\n\nambiguities in this Agreement against the Party that drafted it has no application and is  expressly waived. If any claim is made by a Party relating \nto any conflict, omission or ambiguity  in the provisions of this Agreement, no presumption or burden of proof or persuasion will be  implied \nbecause this Agreement was prepared by or at the request of any Party or its counsel.   \n10.14. Specific Performance . The parties hereto acknowledge and agree that  irreparable damage would occur if any of the provisions of this \nAgreement are not performed in  accordance with their specific terms and that any breach of this Agreement could not be adequately  compensated \nin all cases by monetary damages alone. Accordingly, in addition to any other right or  remedy to which a party hereto may be entitled, at law or in \nequity, it shall be entitled to  enforce any provision of this Agreement by a decree of specific performance and to temporary,  preliminary and\n\n10.5. Severability . If any term or other provision of this Agreement is invalid,  illegal or incapable of being enforced by any Law or public policy, all \nother terms and provisions  of this Agreement shall nevertheless remain in full force and effect for so long as the economic or  legal substance of \nthe transactions contemplated by this Agreement is not affected in any manner  materially adverse to either party hereto. Upon such determination \nthat any term or other  provision is invalid, illegal or incapable of being enforced, the parties hereto shall negotiate in  good faith to modify this \nAgreement so as to effect the original intent of the parties as closely  as possible in an acceptable manner in order that the transactions \ncontemplated by this Agreement  are consummated as originally contemplated to the greatest extent possible.   \n10.6. Entire Agreement . This Agreement constitutes the entire agreement of the  Parties hereto with respect to the subject matter hereof and\n\nor (b) by a waiver in accordance  with Section 10.9.   \n10.9. Waiver . Either Party may (a) extend the time for the performance of any of the  obligations or other acts of the other Party, (b) waive any \ninaccuracies in the representations and  warranties of the other Party contained herein or in any document delivered by the other party  pursuant \nhereto or (c) waive compliance with any of the agreements of the other Party or conditions  to such Party \u2019s obligations contained herein. Any such \nextension or waiver shall be valid only if  set forth in an instrument in writing signed by the Party to be bound thereby. No waiver of any  \nrepresentation, warranty, agreement, condition or obligation granted pursuant to this Section 10.9  or otherwise in accordance with this Agreement \nshall be construed as a waiver of any prior or  subsequent breach of such representation, warranty, agreement, condition or obligation or any other"
}